sample_text/__init__.py
sample_text/_version.py
tests/__init__.py
tests/test_sample_text.py
sample_text-0.1.0.dist-info/METADATA
sample_text-0.1.0.dist-info/WHEEL
sample_text-0.1.0.dist-info/top_level.txt
sample_text-0.1.0.dist-info/RECORD
